{"cameraMode":{"drawMode":0,"name":"Shaded","section":"Shading Mode"},"sceneLighting":true,"audioPlay":false,"sceneViewState":{"m_AlwaysRefresh":false,"showFog":true,"showSkybox":true,"showFlares":true,"showImageEffects":true,"showParticleSystems":true,"showVisualEffectGraphs":true,"m_FxEnabled":true},"in2DMode":false,"pivot":{"x":18.875572204589845,"y":4.806197166442871,"z":-6.176079750061035},"rotation":{"x":0.09498404711484909,"y":-0.5296786427497864,"z":0.059841785579919818,"w":0.8407389521598816},"size":1.931817650794983,"orthographic":false}